mcp/__init__.py
mcp/py.typed
mcp/types.py
mcp/cli/__init__.py
mcp/cli/claude.py
mcp/cli/cli.py
mcp/client/__init__.py
mcp/client/__main__.py
mcp/client/session.py
mcp/client/session_group.py
mcp/client/sse.py
mcp/client/streamable_http.py
mcp/client/websocket.py
mcp/client/stdio/__init__.py
mcp/client/stdio/win32.py
mcp/etdi/__init__.py
mcp/etdi/events.py
mcp/etdi/exceptions.py
mcp/etdi/types.py
mcp/etdi/types_extensions.py
mcp/etdi/cli/__init__.py
mcp/etdi/cli/etdi_cli.py
mcp/etdi/client/__init__.py
mcp/etdi/client/approval_manager.py
mcp/etdi/client/etdi_client.py
mcp/etdi/client/secure_session.py
mcp/etdi/client/secure_transports.py
mcp/etdi/client/verifier.py
mcp/etdi/crypto/__init__.py
mcp/etdi/crypto/key_exchange.py
mcp/etdi/crypto/key_manager.py
mcp/etdi/crypto/request_signer.py
mcp/etdi/inspector/__init__.py
mcp/etdi/inspector/call_stack_verifier.py
mcp/etdi/inspector/oauth_validator.py
mcp/etdi/inspector/security_analyzer.py
mcp/etdi/inspector/token_debugger.py
mcp/etdi/oauth/__init__.py
mcp/etdi/oauth/auth0.py
mcp/etdi/oauth/azure.py
mcp/etdi/oauth/base.py
mcp/etdi/oauth/custom.py
mcp/etdi/oauth/manager.py
mcp/etdi/oauth/okta.py
mcp/etdi/server/__init__.py
mcp/etdi/server/middleware.py
mcp/etdi/server/secure_server.py
mcp/etdi/server/token_manager.py
mcp/etdi/server/tool_provider.py
mcp/server/__init__.py
mcp/server/__main__.py
mcp/server/models.py
mcp/server/session.py
mcp/server/sse.py
mcp/server/stdio.py
mcp/server/streamable_http.py
mcp/server/streamable_http_manager.py
mcp/server/streaming_asgi_transport.py
mcp/server/websocket.py
mcp/server/auth/__init__.py
mcp/server/auth/errors.py
mcp/server/auth/json_response.py
mcp/server/auth/provider.py
mcp/server/auth/routes.py
mcp/server/auth/settings.py
mcp/server/auth/handlers/__init__.py
mcp/server/auth/handlers/authorize.py
mcp/server/auth/handlers/metadata.py
mcp/server/auth/handlers/register.py
mcp/server/auth/handlers/revoke.py
mcp/server/auth/handlers/token.py
mcp/server/auth/middleware/__init__.py
mcp_etdi-1.0.1.dist-info/METADATA
mcp_etdi-1.0.1.dist-info/WHEEL
mcp_etdi-1.0.1.dist-info/entry_points.txt
mcp_etdi-1.0.1.dist-info/licenses/LICENSE
mcp_etdi-1.0.1.dist-info/RECORD
