Metadata-Version: 2.4
Name: mcp-etdi
Version: 1.0.1
Summary: Model Context Protocol Python SDK with ETDI security enhancements
Project-URL: Homepage, https://github.com/modelcontextprotocol/python-sdk
Project-URL: Documentation, https://modelcontextprotocol.io/python
Project-URL: Repository, https://github.com/modelcontextprotocol/python-sdk
Project-URL: Issues, https://github.com/modelcontextprotocol/python-sdk/issues
Author-email: Anthropic <support@anthropic.com>
License-Expression: MIT
License-File: LICENSE
Keywords: ai,etdi,llm,mcp,model-context-protocol,oauth,security
Classifier: Development Status :: 4 - Beta
Classifier: Intended Audience :: Developers
Classifier: License :: OSI Approved :: MIT License
Classifier: Programming Language :: Python :: 3
Classifier: Programming Language :: Python :: 3.9
Classifier: Programming Language :: Python :: 3.10
Classifier: Programming Language :: Python :: 3.11
Classifier: Programming Language :: Python :: 3.12
Classifier: Topic :: Internet :: WWW/HTTP :: HTTP Servers
Classifier: Topic :: Security
Classifier: Topic :: Software Development :: Libraries :: Python Modules
Requires-Python: >=3.9
Requires-Dist: anyio>=3.0.0
Requires-Dist: click>=8.0.0
Requires-Dist: cryptography>=41.0.0
Requires-Dist: httpx-sse>=0.4.0
Requires-Dist: httpx>=0.24.0
Requires-Dist: pydantic-settings>=2.0.0
Requires-Dist: pydantic>=2.0.0
Requires-Dist: pyjwt[crypto]>=2.8.0
Requires-Dist: python-jose[cryptography]>=3.3.0
Requires-Dist: python-multipart>=0.0.6
Requires-Dist: typing-extensions>=4.0.0
Provides-Extra: cli
Requires-Dist: typer>=0.9.0; extra == 'cli'
Provides-Extra: client
Requires-Dist: httpx-sse>=0.4.0; extra == 'client'
Provides-Extra: dev
Requires-Dist: black>=23.0.0; extra == 'dev'
Requires-Dist: isort>=5.12.0; extra == 'dev'
Requires-Dist: mypy>=1.0.0; extra == 'dev'
Requires-Dist: pytest-asyncio>=0.21.0; extra == 'dev'
Requires-Dist: pytest-cov>=4.0.0; extra == 'dev'
Requires-Dist: pytest-examples>=0.0.5; extra == 'dev'
Requires-Dist: pytest>=7.0.0; extra == 'dev'
Requires-Dist: ruff>=0.1.0; extra == 'dev'
Requires-Dist: typer>=0.9.0; extra == 'dev'
Provides-Extra: docs
Requires-Dist: black>=23.0.0; extra == 'docs'
Requires-Dist: cairosvg>=2.5.0; extra == 'docs'
Requires-Dist: mkdocs-glightbox>=0.3.4; extra == 'docs'
Requires-Dist: mkdocs-material[imaging]>=9.0.0; extra == 'docs'
Requires-Dist: mkdocs>=1.5.0; extra == 'docs'
Requires-Dist: mkdocstrings[python]>=0.20.0; extra == 'docs'
Requires-Dist: pycairo>=1.20.0; extra == 'docs'
Requires-Dist: ruff>=0.1.0; extra == 'docs'
Provides-Extra: server
Requires-Dist: fastapi>=0.100.0; extra == 'server'
Requires-Dist: pydantic-settings>=2.0.0; extra == 'server'
Requires-Dist: sse-starlette>=2.0.0; extra == 'server'
Requires-Dist: starlette>=0.27.0; extra == 'server'
Requires-Dist: uvicorn[standard]>=0.20.0; extra == 'server'
